iottycloud/__init.py__
iottycloud/cloudapi.py
iottycloud/device.py
iottycloud/errors.py
iottycloud/lightswitch.py
iottycloud/py.typed
iottycloud/shutter.py
iottycloud/utils.py
iottycloud/verbs.py
iottycloud-0.2.1.dist-info/METADATA
iottycloud-0.2.1.dist-info/WHEEL
iottycloud-0.2.1.dist-info/licenses/LICENSE
iottycloud-0.2.1.dist-info/RECORD
