Metadata-Version: 2.3
Name: iottycloud
Version: 0.2.1
Summary: A Python library to interact with iotty CloudApi
Project-URL: Homepage, https://github.com/pburgio/iottycloud
Project-URL: Bug Tracker, https://github.com/pburgio/iottycloud/issues
Author-email: Paolo Burgio <paolo.burgio@gmail.com>, Luca Marzaduri <luca.marzaduri@iotty.com>, Shapour Nemati <shapour.nemati@iotty.com>
License-File: LICENSE
Classifier: License :: OSI Approved :: GNU Affero General Public License v3
Classifier: Operating System :: OS Independent
Classifier: Programming Language :: Python :: 3
Requires-Python: >=3.7
